{
  "race_id": 185,
  "generated_at": "2025-10-21T10:54:53Z",
  "schema": "v3.3",
  "drivers": [
    {
      "driver_id": 227,
      "team": "",
      "best_time_ms": 79600,
      "best_time_raw": "1:19.600",
      "source_session": "Q3",
      "perf_pct": 100.378
    },
    {
      "driver_id": 299,
      "team": "",
      "best_time_ms": 80300,
      "best_time_raw": "1:20.300",
      "source_session": "Q1",
      "perf_pct": 101.261
    },
    {
      "driver_id": 437,
      "team": "",
      "best_time_ms": 79300,
      "best_time_raw": "1:19.300",
      "source_session": "Q3",
      "perf_pct": 100.0
    },
    {
      "driver_id": 441,
      "team": "",
      "best_time_ms": 80200,
      "best_time_raw": "1:20.200",
      "source_session": "Q4",
      "perf_pct": 101.135
    },
    {
      "driver_id": 448,
      "team": "",
      "best_time_ms": 80000,
      "best_time_raw": "1:20.000",
      "source_session": "Q4",
      "perf_pct": 100.883
    },
    {
      "driver_id": 457,
      "team": "",
      "best_time_ms": 80500,
      "best_time_raw": "1:20.500",
      "source_session": "Q1",
      "perf_pct": 101.513
    },
    {
      "driver_id": 293,
      "team": "",
      "best_time_ms": 81600,
      "best_time_raw": "1:21.600",
      "source_session": "Q3",
      "perf_pct": 102.9
    },
    {
      "driver_id": 355,
      "team": "",
      "best_time_ms": 80200,
      "best_time_raw": "1:20.200",
      "source_session": "Q3",
      "perf_pct": 101.135
    },
    {
      "driver_id": 383,
      "team": "",
      "best_time_ms": 83100,
      "best_time_raw": "1:23.100",
      "source_session": "Q4",
      "perf_pct": 104.792
    },
    {
      "driver_id": 394,
      "team": "",
      "best_time_ms": 80200,
      "best_time_raw": "1:20.200",
      "source_session": "Q4",
      "perf_pct": 101.135
    },
    {
      "driver_id": 396,
      "team": "",
      "best_time_ms": 79300,
      "best_time_raw": "1:19.300",
      "source_session": "Q3",
      "perf_pct": 100.0
    },
    {
      "driver_id": 401,
      "team": "",
      "best_time_ms": 82700,
      "best_time_raw": "1:22.700",
      "source_session": "Q4",
      "perf_pct": 104.288
    },
    {
      "driver_id": 409,
      "team": "",
      "best_time_ms": 81300,
      "best_time_raw": "1:21.300",
      "source_session": "Q4",
      "perf_pct": 102.522
    },
    {
      "driver_id": 418,
      "team": "",
      "best_time_ms": 79900,
      "best_time_raw": "1:19.900",
      "source_session": "Q4",
      "perf_pct": 100.757
    },
    {
      "driver_id": 426,
      "team": "",
      "best_time_ms": 80900,
      "best_time_raw": "1:20.900",
      "source_session": "Q4",
      "perf_pct": 102.018
    },
    {
      "driver_id": 430,
      "team": "",
      "best_time_ms": 80100,
      "best_time_raw": "1:20.100",
      "source_session": "Q2",
      "perf_pct": 101.009
    },
    {
      "driver_id": 443,
      "team": "",
      "best_time_ms": 82000,
      "best_time_raw": "1:22.000",
      "source_session": "Q4",
      "perf_pct": 103.405
    },
    {
      "driver_id": 453,
      "team": "",
      "best_time_ms": 81400,
      "best_time_raw": "1:21.400",
      "source_session": "Q3",
      "perf_pct": 102.648
    },
    {
      "driver_id": 463,
      "team": "",
      "best_time_ms": 81500,
      "best_time_raw": "1:21.500",
      "source_session": "Q4",
      "perf_pct": 102.774
    },
    {
      "driver_id": 464,
      "team": "",
      "best_time_ms": 82100,
      "best_time_raw": "1:22.100",
      "source_session": "Q2",
      "perf_pct": 103.531
    },
    {
      "driver_id": 474,
      "team": "",
      "best_time_ms": 84600,
      "best_time_raw": "1:24.600",
      "source_session": "Q3",
      "perf_pct": 106.683
    },
    {
      "driver_id": 475,
      "team": "",
      "best_time_ms": 81000,
      "best_time_raw": "1:21.000",
      "source_session": "Q4",
      "perf_pct": 102.144
    },
    {
      "driver_id": 487,
      "team": "",
      "best_time_ms": 81200,
      "best_time_raw": "1:21.200",
      "source_session": "Q3",
      "perf_pct": 102.396
    },
    {
      "driver_id": 462,
      "team": "",
      "best_time_ms": 80900,
      "best_time_raw": "1:20.900",
      "source_session": "Q4",
      "perf_pct": 102.018
    }
  ]
}